Metadata-Version: 2.1
Name: mapillary-nearby
Version: 1.0.0
Summary: Get pictures near an area
Home-page: https://github.com/talwrii/mapillary-nearby
Author: @readwithai
Author-email: talwrii@gmail.com
License: MIT
Keywords: mapilliary,wallpaper,background,nearby
